ita_converter.py
ita_converter-0.9.3.dist-info/WHEEL
ita_converter-0.9.3.dist-info/METADATA
ita_converter-0.9.3.dist-info/RECORD
