Metadata-Version: 2.1
Name: ita-converter
Version: 0.9.3
Summary: ita-converter - convert your images to ASCII art easily!
Author-email: Lyubomir T <ternavski103@gmail.com>
Classifier: Development Status :: 5 - Production/Stable
Classifier: Programming Language :: Python
Requires-Dist: numpy
Requires-Dist: Pillow
